UniFix/UniFix.py
UniFix/UniFix_test.py
UniFix/__init__.py
UniFix/errors.py
UniFix/test_uni.py
UniFix/Fix/__init__.py
UniFix/Fix/chat.py
UniFix/Fix/extract_code.py
UniFix/Fix/system.py
UniFix/Output/__init__.py
UniFix/Output/logs.py
UniFix/Output/rerun.py
UniFix/Output/shell_logger.py
UniFix/Shell/__init__.py
UniFix/Shell/alias.py
UniFix/Shell/arg_parse.py
UniFix/Shell/const.py
UniFix/Shell/shell.py
UniFix/Shell/utils.py
UniFix/System/__init__.py
UniFix/System/message.py
UniFix/Uni/__init__.py
UniFix/Uni/errors.py
UniFix/Uni/helpconstants.py
UniFix/Uni/maninfo.py
UniFix/Uni/matcher.py
UniFix/Uni/option.py
UniFix/User/__init__.py
UniFix/User/ui.py
unifix-0.1.1.dist-info/LICENSE
unifix-0.1.1.dist-info/METADATA
unifix-0.1.1.dist-info/WHEEL
unifix-0.1.1.dist-info/entry_points.txt
unifix-0.1.1.dist-info/top_level.txt
unifix-0.1.1.dist-info/RECORD
